dialex
