Metadata-Version: 1.1
Name: dialex
Version: 1.0.0
Summary: Python Client for HyperLab Dialex API
Home-page: https://github.com/HyperLab-Solutions-Sdn-Bhd/dialex-sdk-python
Author: Riyadh Al Nur
Author-email: riyadh.alnur@hyperlab.xyz
License: MIT License
Keywords: hyperlab,python,sdk,nlp
Platform: UNKNOWN
Classifier: Intended Audience :: Developers
Classifier: License :: OSI Approved :: MIT License
Classifier: Operating System :: OS Independent
Classifier: Programming Language :: Python
Classifier: Programming Language :: Python :: 2
Classifier: Programming Language :: Python :: 2.7
Classifier: Programming Language :: Python :: 3
Classifier: Programming Language :: Python :: 3.2
Classifier: Programming Language :: Python :: 3.3
Classifier: Programming Language :: Python :: 3.4
Classifier: Programming Language :: Python :: 3.5
Classifier: Programming Language :: Python :: 3.6
Classifier: Topic :: Internet
Classifier: Topic :: Internet :: WWW/HTTP
Classifier: Development Status :: 5 - Production/Stable
